nonebot_plugin_sudo/__init__.py
nonebot_plugin_sudo/config.py
nonebot_plugin_sudo-1.0.6.dist-info/LICENSE
nonebot_plugin_sudo-1.0.6.dist-info/METADATA
nonebot_plugin_sudo-1.0.6.dist-info/WHEEL
nonebot_plugin_sudo-1.0.6.dist-info/top_level.txt
nonebot_plugin_sudo-1.0.6.dist-info/RECORD
