Metadata-Version: 2.1
Name: nonebot-plugin-sudo
Version: 1.0.6
Summary: XDbot2 SUDO 插件独立版
Author-email: This is XiaoDeng <1744793737@qq.com>
License: MIT-License
Keywords: nonebot2,onebot
Classifier: Programming Language :: Python :: 3
Requires-Python: >=3.8
License-File: LICENSE
Requires-Dist: nonebot2
Requires-Dist: nonebot-adapter-onebot
